[
  {
    "text": "[IDENTIFYING THE WRITER'S VIEWS]\n",
    "isBold": true
  },
  {
    "text": "05\n",
    "isBold": true
  },
  {
    "text": "به گزاره‌های A تا C نگاه کنید. همه‌ی آن‌ها اطلاعاتی درباره رسانه‌های اجتماعی ارائه می‌دهند. تنها یکی از آن‌ها شامل دیدگاه شخصی نویسنده است. کدام یک؟\n",
    "isBold": false
  },
  {
    "text": "A ",
    "isBold": true
  },
  {
    "text": "«ویبو» توییترِ چین است، اما در واقع دو برابر توییتر کاربر دارد.\n",
    "isBold": false
  },
  {
    "text": "B ",
    "isBold": true
  },
  {
    "text": "در ایالات متحده، بیش از ۷۰ درصد جمعیت دارای حساب کاربری در رسانه‌های اجتماعی هستند.\n",
    "isBold": false
  },
  {
    "text": "C ",
    "isBold": true
  },
  {
    "text": "بیش از ۱.۵ میلیارد نفر وقت خود را در فیس‌بوک تلف می‌کنند.\nآیا نویسنده مستقیماً نظر خود را بیان می‌کند؟ چگونه می‌توانید نظر او را تشخیص دهید؟\n\n",
    "isBold": false
  },
  {
    "text": "⚫این تمرین توانایی شما را در تصمیم‌گیری درباره اینکه آیا گزاره‌ها بازتاب‌دهنده دیدگاه‌های نویسنده هستند یا خیر، می‌سنجد. این دیدگاه‌ها به طور مستقیم بیان نخواهند شد.",
    "isBold": false
  }
]