[
  {
    "text": "11\n",
    "isBold": true
  },
  {
    "text": "جملات را گوش دهید و تکرار کنید. مراقب تلفظ افعالی که به s ختم می‌شوند باشید.\nآیا کسی در خانواده شما هست که گاهی شما را آزار دهد؟\n-پدرم فوتبال تماشا می‌کند و خیلی فریاد می‌زند.\n-برادرم تمام وقت با کامپیوتر بازی می‌کند.\n-مادرم مدام به من می‌گوید که اتاقم را مرتب کنم.\n\n",
    "isBold": false
  },
  {
    "text": "Track 14\n",
    "isBold": true
  },
  {
    "text": "Examiner:",
    "isBold": true
  },
  {
    "text": " آیا کسی در خانواده شما هست که گاهی شما را آزار دهد؟\n",
    "isBold": false
  },
  {
    "text": "A:",
    "isBold": true
  },
  {
    "text": " پدرم فوتبال تماشا می‌کند و خیلی فریاد می‌زند.\n",
    "isBold": false
  },
  {
    "text": "B:",
    "isBold": true
  },
  {
    "text": " برادرم تمام وقت با کامپیوتر بازی می‌کند.\n",
    "isBold": false
  },
  {
    "text": "C:",
    "isBold": true
  },
  {
    "text": " مادرم مدام به من می‌گوید که اتاقم را مرتب کنم.",
    "isBold": false
  }
]