[
  {
    "text": "EXAM SKILLS\n11\n",
    "isInteractive": false,
    "isBold": true,
    "isBlank": false,
    "isLineThrough": false,
    "translation": null,
    "explanation": null
  },
  {
    "text": "The pictures show the process of making cherry jam.\nDescribe the process.\nRemember to:\n•\tinclude an introduction and an overview\n•\tuse the ",
    "isInteractive": false,
    "isBold": false,
    "isBlank": false,
    "isLineThrough": false,
    "translation": null,
    "explanation": null
  },
  {
    "text": "present simple passive",
    "isInteractive": true,
    "isBold": false,
    "isBlank": false,
    "isLineThrough": false,
    "translation": "حال ساده مجهول",
    "explanation": "ساختاری که در آن مفعول در جایگاه فاعل قرار می‌گیرد (am/is/are + p.p) و برای توصیف فرآیندهای صنعتی بسیار رایج است."
  },
  {
    "text": "\n•\tuse ",
    "isInteractive": false,
    "isBold": false,
    "isBlank": false,
    "isLineThrough": false,
    "translation": null,
    "explanation": null
  },
  {
    "text": "sequencing expressions",
    "isInteractive": true,
    "isBold": false,
    "isBlank": false,
    "isLineThrough": false,
    "translation": "عبارات ترتیب‌بندی",
    "explanation": "کلماتی مانند First, Then, After that که برای نشان دادن ترتیب مراحل در یک فرآیند استفاده می‌شوند."
  },
  {
    "text": "\n•\twrite 150 words.\n\n",
    "isInteractive": false,
    "isBold": false,
    "isBlank": false,
    "isLineThrough": false,
    "translation": null,
    "explanation": null
  },
  {
    "text": "TIP 11\n",
    "isInteractive": false,
    "isBold": true,
    "isBlank": false,
    "isLineThrough": false,
    "translation": null,
    "explanation": null
  },
  {
    "text": "Use the words on the pictures and diagrams in your answer. They are given to help you.\n\n",
    "isInteractive": false,
    "isBold": false,
    "isBlank": false,
    "isLineThrough": false,
    "translation": null,
    "explanation": null
  },
  {
    "text": "Sample answer\n",
    "isInteractive": false,
    "isBold": true,
    "isBlank": false,
    "isLineThrough": false,
    "translation": null,
    "explanation": null
  },
  {
    "text": "The pictures show the ",
    "isInteractive": false,
    "isBold": false,
    "isBlank": false,
    "isLineThrough": false,
    "translation": null,
    "explanation": null
  },
  {
    "text": "stages",
    "isInteractive": true,
    "isBold": false,
    "isBlank": false,
    "isLineThrough": false,
    "translation": "مراحل",
    "explanation": "بخش‌های مختلف یک فرآیند یا دوره زمانی."
  },
  {
    "text": " in the ",
    "isInteractive": false,
    "isBold": false,
    "isBlank": false,
    "isLineThrough": false,
    "translation": null,
    "explanation": null
  },
  {
    "text": "production",
    "isInteractive": true,
    "isBold": false,
    "isBlank": false,
    "isLineThrough": false,
    "translation": "تولید",
    "explanation": "فرآیند ساخت یا استخراج چیزی در مقیاس صنعتی."
  },
  {
    "text": " of cherry jam. There are a number of processes ",
    "isInteractive": false,
    "isBold": false,
    "isBlank": false,
    "isLineThrough": false,
    "translation": null,
    "explanation": null
  },
  {
    "text": "involved",
    "isInteractive": true,
    "isBold": false,
    "isBlank": false,
    "isLineThrough": false,
    "translation": "دخیل / مرتبط",
    "explanation": "اشاره به کارها یا بخش‌هایی دارد که جزئی از یک فعالیت هستند."
  },
  {
    "text": ", from picking the fruit from the tree to putting it into jars ready to sell.\nFirst, a sheet is ",
    "isInteractive": false,
    "isBold": false,
    "isBlank": false,
    "isLineThrough": false,
    "translation": null,
    "explanation": null
  },
  {
    "text": "spread",
    "isInteractive": true,
    "isBold": false,
    "isBlank": false,
    "isLineThrough": false,
    "translation": "پهن شده",
    "explanation": "قسمت سوم فعل spread به معنای گستردن یا پخش کردن روی یک سطح."
  },
  {
    "text": " on the ground under the tree and the tree is ",
    "isInteractive": false,
    "isBold": false,
    "isBlank": false,
    "isLineThrough": false,
    "translation": null,
    "explanation": null
  },
  {
    "text": "shaken",
    "isInteractive": true,
    "isBold": false,
    "isBlank": false,
    "isLineThrough": false,
    "translation": "تکان داده شده",
    "explanation": "قسمت سوم فعل shake؛ در اینجا به لرزاندن درخت برای ریختن میوه‌ها اشاره دارد."
  },
  {
    "text": " by a mechanical arm to get the cherries down from the tree. Then, the cherries are collected and ",
    "isInteractive": false,
    "isBold": false,
    "isBlank": false,
    "isLineThrough": false,
    "translation": null,
    "explanation": null
  },
  {
    "text": "transported",
    "isInteractive": true,
    "isBold": false,
    "isBlank": false,
    "isLineThrough": false,
    "translation": "حمل و نقل شده",
    "explanation": "انتقال کالا یا افراد از یک مکان به مکان دیگر."
  },
  {
    "text": " by ",
    "isInteractive": false,
    "isBold": false,
    "isBlank": false,
    "isLineThrough": false,
    "translation": null,
    "explanation": null
  },
  {
    "text": "lorry",
    "isInteractive": true,
    "isBold": false,
    "isBlank": false,
    "isLineThrough": false,
    "translation": "کامیون",
    "explanation": "واژه‌ای بریتانیایی برای وسایل نقلیه بزرگ باری (معادل truck در آمریکایی)."
  },
  {
    "text": " to the processing plant. There the leaves and the ",
    "isInteractive": false,
    "isBold": false,
    "isBlank": false,
    "isLineThrough": false,
    "translation": null,
    "explanation": null
  },
  {
    "text": "stems",
    "isInteractive": true,
    "isBold": false,
    "isBlank": false,
    "isLineThrough": false,
    "translation": "ساقه‌ها / دم میوه",
    "explanation": "بخش گیاهی که میوه را به شاخه متصل می‌کند."
  },
  {
    "text": " are removed and then the ",
    "isInteractive": false,
    "isBold": false,
    "isBlank": false,
    "isLineThrough": false,
    "translation": null,
    "explanation": null
  },
  {
    "text": "stone",
    "isInteractive": true,
    "isBold": false,
    "isBlank": false,
    "isLineThrough": false,
    "translation": "هسته",
    "explanation": "هسته سخت وسط میوه‌هایی مانند گیلاس، هلو یا زردآلو."
  },
  {
    "text": " is taken out with a metal ",
    "isInteractive": false,
    "isBold": false,
    "isBlank": false,
    "isLineThrough": false,
    "translation": null,
    "explanation": null
  },
  {
    "text": "spike",
    "isInteractive": true,
    "isBold": false,
    "isBlank": false,
    "isLineThrough": false,
    "translation": "سیخک / جسم نوک‌تیز",
    "explanation": "یک قطعه فلزی یا چوبی بلند و نوک‌تیز."
  },
  {
    "text": ". Next, sugar, lemon juice and ",
    "isInteractive": false,
    "isBold": false,
    "isBlank": false,
    "isLineThrough": false,
    "translation": null,
    "explanation": null
  },
  {
    "text": "pectin",
    "isInteractive": true,
    "isBold": false,
    "isBlank": false,
    "isLineThrough": false,
    "translation": "پکتین",
    "explanation": "ماده‌ای طبیعی در میوه‌ها که باعث ژله‌ای شدن و بستن مربا می‌شود."
  },
  {
    "text": " are added to the cherries and the jam is cooked. After that, the quality of the jam is checked and then the jam is put into jars. A ",
    "isInteractive": false,
    "isBold": false,
    "isBlank": false,
    "isLineThrough": false,
    "translation": null,
    "explanation": null
  },
  {
    "text": "lid",
    "isInteractive": true,
    "isBold": false,
    "isBlank": false,
    "isLineThrough": false,
    "translation": "درب (ظرف)",
    "explanation": "پوششی برای بستن دهانه ظرف یا جعبه."
  },
  {
    "text": " is put on top of the jars to keep the jam fresh. Finally, a ",
    "isInteractive": false,
    "isBold": false,
    "isBlank": false,
    "isLineThrough": false,
    "translation": null,
    "explanation": null
  },
  {
    "text": "label",
    "isInteractive": true,
    "isBold": false,
    "isBlank": false,
    "isLineThrough": false,
    "translation": "برچسب",
    "explanation": "کاغذی که روی محصول چسبانده می‌شود و حاوی اطلاعاتی درباره آن است."
  },
  {
    "text": " is added and the jam is ready to be sold in the shops.",
    "isInteractive": false,
    "isBold": false,
    "isBlank": false,
    "isLineThrough": false,
    "translation": null,
    "explanation": null
  }
]