[
  {
    "text": "Calling all fans of Sam West! This famous ",
    "isInteractive": false,
    "isBold": false,
    "translation": null,
    "explanation": null
  },
  {
    "text": "adventure writer",
    "isInteractive": true,
    "isBold": false,
    "translation": "نویسنده ماجراجویی",
    "explanation": "شخصی که داستان‌ها، کتاب‌ها یا فیلم‌هایی با محوریت ماجراها و سفرهای هیجان‌انگیز می‌نویسد."
  },
  {
    "text": " will be in Westfield shopping centre tomorrow in Bookworms Bookshop on the ",
    "isInteractive": false,
    "isBold": false,
    "translation": null,
    "explanation": null
  },
  {
    "text": "first floor",
    "isInteractive": true,
    "isBold": false,
    "translation": "طبقه اول",
    "explanation": "اولین طبقه بالای همکف (بسته به منطقه ممکن است به عنوان ground floor نیز شناخته شود، اما در متن اشاره به طبقه بالای همکف دارد)."
  },
  {
    "text": ". He will be ",
    "isInteractive": false,
    "isBold": false,
    "translation": null,
    "explanation": null
  },
  {
    "text": "signing copies",
    "isInteractive": true,
    "isBold": false,
    "translation": "امضا کردن نسخه‌ها",
    "explanation": "رسمی کردن نسخه‌های کتاب یا اثر خود با امضا، معمولاً در یک رویداد تبلیغاتی برای طرفداران."
  },
  {
    "text": " of his latest book, Timed Out. He is ",
    "isInteractive": false,
    "isBold": false,
    "translation": null,
    "explanation": null
  },
  {
    "text": "expected to get there",
    "isInteractive": true,
    "isBold": false,
    "translation": "انتظار می‌رود برسد",
    "explanation": "مترادف با 'is likely to arrive' یا 'is anticipated to be there'، به معنای زمان یا مکان مورد انتظار حضور کسی."
  },
  {
    "text": " at ",
    "isInteractive": false,
    "isBold": false,
    "translation": null,
    "explanation": null
  },
  {
    "text": "quarter past two",
    "isInteractive": true,
    "isBold": false,
    "translation": "ساعت دو و ربع",
    "explanation": "زمانی که ۱۵ دقیقه از ساعت ۲ گذشته باشد (۲:۱۵)."
  },
  {
    "text": " and will stay until ",
    "isInteractive": false,
    "isBold": false,
    "translation": null,
    "explanation": null
  },
  {
    "text": "half past three",
    "isInteractive": true,
    "isBold": false,
    "translation": "ساعت سه و نیم",
    "explanation": "زمانی که ۳۰ دقیقه از ساعت ۳ گذشته باشد (۳:۳۰)."
  },
  {
    "text": ". Get there as ",
    "isInteractive": false,
    "isBold": false,
    "translation": null,
    "explanation": null
  },
  {
    "text": "soon as you can",
    "isInteractive": true,
    "isBold": false,
    "translation": "به محض اینکه توانستید",
    "explanation": "به معنی 'در اسرع وقت ممکن' یا 'در سریع‌ترین زمان'. یک عبارت رایج در زبان انگلیسی محاوره‌ای و رسمی."
  },
  {
    "text": " because ",
    "isInteractive": false,
    "isBold": false,
    "translation": null,
    "explanation": null
  },
  {
    "text": "queues will start to form",
    "isInteractive": true,
    "isBold": false,
    "translation": "صف‌ها شروع به تشکیل شدن خواهند کرد",
    "explanation": "به معنای اینکه افراد برای ملاقات یا دریافت امضا شروع به صف کشیدن می‌کنند."
  },
  {
    "text": " as ",
    "isInteractive": false,
    "isBold": false,
    "translation": null,
    "explanation": null
  },
  {
    "text": "early as noon",
    "isInteractive": true,
    "isBold": false,
    "translation": "حتی از ظهر زودتر",
    "explanation": "به معنای 'از ساعت ۱۲ ظهر' و نشان‌دهنده این است که صف‌ها زودتر از حد انتظار شروع می‌شوند."
  },
  {
    "text": ". Don't ",
    "isInteractive": false,
    "isBold": false,
    "translation": null,
    "explanation": null
  },
  {
    "text": "miss this great opportunity",
    "isInteractive": true,
    "isBold": false,
    "translation": "این فرصت عالی را از دست ندهید",
    "explanation": "یک عبارت تشویقی به معنای از دست ندادن یک شانس یا موقعیت مهم."
  },
  {
    "text": " to meet everyone's favourite writer!",
    "isInteractive": false,
    "isBold": false,
    "translation": null,
    "explanation": null
  }
]