[
  {
    "text": "GRAMMAR FOCUS: MODALS OF POSSIBILITY AND ABILITY\n",
    "isBold": true,
    "isInteractive": false
  },
  {
    "text": "11\n",
    "isBold": true,
    "isInteractive": false
  },
  {
    "text": "Find two more examples of ",
    "isBold": false,
    "isInteractive": false
  },
  {
    "text": "modals of possibility",
    "isInteractive": true,
    "isBold": false,
    "translation": "افعال کمکی وجهی بیانگر احتمال",
    "explanation": "افعالی مانند may، might و could که برای بیان احتمالات و عدم قطعیت در جملات به کار می‌روند."
  },
  {
    "text": " (look in paragraphs A and F).\n",
    "isBold": false,
    "isInteractive": false
  },
  {
    "text": "12\n",
    "isBold": true,
    "isInteractive": false
  },
  {
    "text": "Find more examples of ",
    "isBold": false,
    "isInteractive": false
  },
  {
    "text": "modals of ability",
    "isInteractive": true,
    "isBold": false,
    "translation": "افعال کمکی وجهی بیانگر توانایی",
    "explanation": "افعالی مانند can و could که برای نشان دادن توانایی انجام کاری در زمان حال یا گذشته استفاده می‌شوند."
  },
  {
    "text": " in paragraph B.\n\n",
    "isBold": false,
    "isInteractive": false
  },
  {
    "text": "•",
    "isBold": false,
    "isInteractive": false
  },
  {
    "text": "The modals can and could are used to talk about ",
    "isBold": false,
    "isInteractive": false
  },
  {
    "text": "ability",
    "isInteractive": true,
    "isBold": false,
    "translation": "توانایی",
    "explanation": "مهارت یا قدرت لازم برای انجام کاری؛ در آیلتس برای توصیف ویژگی‌ها و مهارت‌های فردی بسیار کاربردی است."
  },
  {
    "text": " in the present and past.\nDolphins can tell when a woman is pregnant.\nYang Yun found she ",
    "isBold": false,
    "isInteractive": false
  },
  {
    "text": "couldn't move",
    "isInteractive": true,
    "isBold": false,
    "translation": "نمی‌توانست حرکت دهد",
    "explanation": "شکل گذشته منفی از فعل modal توانایی (could) که برای بیان عدم توانایی در گذشته استفاده شده است."
  },
  {
    "text": " her legs ",
    "isBold": false,
    "isInteractive": false
  },
  {
    "text": "due to",
    "isInteractive": true,
    "isBold": false,
    "translation": "به دلیلِ / ناشی از",
    "explanation": "یک حرف اضافه (preposition) بسیار رایج در رایتینگ آیلتس برای بیان علت و معلول."
  },
  {
    "text": " the freezing temperatures.\n\n",
    "isBold": false,
    "isInteractive": false
  },
  {
    "text": "•",
    "isBold": false,
    "isInteractive": false
  },
  {
    "text": "Modal verbs may, might and could are used when something is ",
    "isBold": false,
    "isInteractive": false
  },
  {
    "text": "possible",
    "isInteractive": true,
    "isBold": false,
    "translation": "امکان‌پذیر / محتمل",
    "explanation": "صفتی که نشان می‌دهد چیزی می‌تواند اتفاق بیفتد اما قطعی نیست."
  },
  {
    "text": " but not ",
    "isBold": false,
    "isInteractive": false
  },
  {
    "text": "certain",
    "isInteractive": true,
    "isBold": false,
    "translation": "قطعی / مطمئن",
    "explanation": "بیانگر اطمینان صد درصدی؛ متضاد آن در جملات احتمالی استفاده می‌شود."
  },
  {
    "text": ":\nExperts think dolphins ",
    "isBold": false,
    "isInteractive": false
  },
  {
    "text": "may understand",
    "isInteractive": true,
    "isBold": false,
    "translation": "ممکن است درک کنند",
    "explanation": "ترکیب فعل وجهی may با فعل اصلی برای بیان حدس و گمان علمی."
  },
  {
    "text": " that humans are similar to them",
    "isBold": false,
    "isInteractive": false
  }
]